archivist.py
ao3_archivist-0.1.1.dist-info/LICENSE
ao3_archivist-0.1.1.dist-info/METADATA
ao3_archivist-0.1.1.dist-info/WHEEL
ao3_archivist-0.1.1.dist-info/entry_points.txt
ao3_archivist-0.1.1.dist-info/top_level.txt
ao3_archivist-0.1.1.dist-info/RECORD
