Metadata-Version: 2.1
Name: ao3-archivist
Version: 0.1.1
Summary: Reading history exporter for AO3
Author-email: fandomdotlove <hello@fandom.love>
License: MIT License        
Project-URL: Homepage, https://gitlab.com/fandomdotlove/ao3-archivist
Classifier: License :: OSI Approved :: MIT License
Classifier: Programming Language :: Python
Classifier: Programming Language :: Python :: 3
Requires-Python: >=3.10.5
License-File: LICENSE
Requires-Dist: beautifulsoup4
Requires-Dist: click
Requires-Dist: lxml
Requires-Dist: requests
Provides-Extra: dev
Requires-Dist: yapf ; extra == 'dev'
